{"version":3,"kind":"Article","sha256":"f2c399e88bc5124ccc334861e0b82a72456778c955faf78536fa5d354744bba8","slug":"index","location":"/content/index.md","dependencies":[],"frontmatter":{"title":"Mi Libro de DataViz","content_includes_title":false,"exports":[{"format":"md","filename":"index.md","url":"/index-2ece7fc3619f06065378814709c656d6.md"}]},"mdast":{"type":"root","children":[{"type":"block","children":[{"type":"paragraph","position":{"start":{"line":3,"column":1},"end":{"line":3,"column":1}},"children":[{"type":"text","value":"Bienvenido a mi libro.","position":{"start":{"line":3,"column":1},"end":{"line":3,"column":1}},"key":"u73vBAJoqv"}],"key":"KKKlpt0f6b"},{"type":"block","children":[{"type":"list","children":[{"type":"listItem","children":[{"type":"link","url":"/","internal":true,"children":[{"type":"text","value":"Mi Libro de DataViz","key":"XIdTSGpVwE"}],"urlSource":"/","key":"HldfdpwW70"}],"key":"y94ZB0jRH9"},{"type":"listItem","children":[{"type":"text","value":"Test","key":"slSUUGKDnD"},{"type":"list","children":[{"type":"listItem","children":[{"type":"link","url":"/test","internal":true,"children":[{"type":"text","value":"Fuentes y características de los datos","key":"DPLQUM3Hdu"}],"urlSource":"/test","dataUrl":"/test.json","protocol":"file","key":"QszzCzgFPW"}],"key":"HCRRUCnP3y"}],"key":"elXVUThsBU"}],"key":"OoNl2LuKCn"}],"key":"AhHCSIsKOy"}],"data":{"part":"toc:project"},"key":"WwddX65UKB"}],"key":"hMFIaQXw0i"}],"key":"IktyBR3CPj"},"references":{"cite":{"order":[],"data":{}}}}